batch_please/__init__.py
batch_please/_version.py
batch_please/batchers.py
batch_please-0.3.1.dist-info/licenses/LICENSE
batch_please-0.3.1.dist-info/METADATA
batch_please-0.3.1.dist-info/WHEEL
batch_please-0.3.1.dist-info/top_level.txt
batch_please-0.3.1.dist-info/RECORD
