Metadata-Version: 2.4
Name: batch_please
Version: 0.3.1
Summary: A package for batch processing with sync and async capabilities
Author-email: David Gillespie <git.atypical244@slmail.me>
Project-URL: Homepage, https://github.com/gillespied/batch_please
Project-URL: Bug Tracker, https://github.com/gillespied/batch_please/issues
Classifier: Programming Language :: Python :: 3
Classifier: License :: OSI Approved :: MIT License
Classifier: Operating System :: OS Independent
Requires-Python: >=3.8
License-File: LICENSE
Requires-Dist: tqdm
Provides-Extra: dev
Requires-Dist: ruff>=0.12.3; extra == "dev"
Requires-Dist: build; extra == "dev"
Requires-Dist: pytest; extra == "dev"
Requires-Dist: pytest-asyncio; extra == "dev"
Requires-Dist: mkdocs; extra == "dev"
Requires-Dist: mkdocs-material; extra == "dev"
Requires-Dist: mkdocstrings[python]; extra == "dev"
Requires-Dist: pre-commit; extra == "dev"
Dynamic: license-file
